LICENSE
MANIFEST.in
README.md
requirements.txt
setup.py
audio_plot_lib/__init__.py
audio_plot_lib/interactive.py
audio_plot_lib/playable.py
audio_plot_lib.egg-info/PKG-INFO
audio_plot_lib.egg-info/SOURCES.txt
audio_plot_lib.egg-info/dependency_links.txt
audio_plot_lib.egg-info/not-zip-safe
audio_plot_lib.egg-info/requires.txt
audio_plot_lib.egg-info/top_level.txt
tests/test_interactive.py
tests/test_playable.py