Metadata-Version: 2.1
Name: audio-plot-lib
Version: 0.1.2
Summary: Plot tools based on audio
Home-page: https://github.com/hassaku/audio-plot-lib
Author: hassaku
Author-email: hassaku.apps@gmail.com
License: MIT
Keywords: audio plot visually-impaired
License-File: LICENSE
